hf_olmo/__init__.py
hf_olmo/configuration_olmo.py
hf_olmo/convert_olmo_to_hf.py
hf_olmo/modeling_olmo.py
hf_olmo/tokenization_olmo_fast.py
olmo/__init__.py
olmo/aliases.py
olmo/beam_search.py
olmo/checkpoint.py
olmo/config.py
olmo/exceptions.py
olmo/initialization.py
olmo/model.py
olmo/optim.py
olmo/py.typed
olmo/tokenizer.py
olmo/torch_util.py
olmo/train.py
olmo/util.py
olmo/version.py
olmo/data/__init__.py
olmo/data/collator.py
olmo/data/iterable_dataset.py
olmo/data/memmap_dataset.py
olmo/eval/__init__.py
olmo/eval/downstream.py
olmo/eval/evaluator.py
olmo-0.2.0.dist-info/LICENSE
olmo-0.2.0.dist-info/METADATA
olmo-0.2.0.dist-info/WHEEL
olmo-0.2.0.dist-info/top_level.txt
olmo-0.2.0.dist-info/RECORD
