Metadata-Version: 2.1
Name: olmo
Version: 0.2.0
Summary: Open Language Model (OLMo)
Author-email: Allen Institute for Artificial Intelligence <olmo@allenai.org>
License: Apache License
Project-URL: Homepage, https://github.com/allenai/LLM
Project-URL: Repository, https://github.com/allenai/LLM
Requires-Python: >=3.8
License-File: LICENSE
Requires-Dist: numpy
Requires-Dist: torch >=2.0
Requires-Dist: torchmetrics
Requires-Dist: tokenizers
Requires-Dist: click
Requires-Dist: rich
Requires-Dist: cached-path
Requires-Dist: beaker-gantry
Requires-Dist: omegaconf
Requires-Dist: wandb
Requires-Dist: logzio-python-handler
Requires-Dist: boto3
Requires-Dist: google-cloud-storage
Requires-Dist: packaging
Requires-Dist: datasets
Requires-Dist: scikit-learn
Requires-Dist: smashed[remote] >=0.21.1
Requires-Dist: msgspec >=0.14.0
Provides-Extra: dev
Requires-Dist: ruff ; extra == 'dev'
Requires-Dist: mypy <1.4,>=1.0 ; extra == 'dev'
Requires-Dist: black <24.0,>=23.1 ; extra == 'dev'
Requires-Dist: isort <5.13,>=5.12 ; extra == 'dev'
Requires-Dist: pytest ; extra == 'dev'
Requires-Dist: pytest-sphinx ; extra == 'dev'
Requires-Dist: twine >=1.11.0 ; extra == 'dev'
Requires-Dist: setuptools ; extra == 'dev'
Requires-Dist: wheel ; extra == 'dev'
Requires-Dist: build ; extra == 'dev'
